pandas_text_comparer/__init__.py
pandas_text_comparer/comparer.py
pandas_text_comparer-0.1.1.dist-info/LICENSE
pandas_text_comparer-0.1.1.dist-info/METADATA
pandas_text_comparer-0.1.1.dist-info/WHEEL
pandas_text_comparer-0.1.1.dist-info/RECORD
