Metadata-Version: 2.1
Name: pandas-text-comparer
Version: 0.1.1
Summary: Compare texts within a pandas DataFrame, highlighting changes and computing similarity ratios
License: MIT
Author: n-splv
Author-email: nick.maykr@gmail.com
Requires-Python: >=3.10,<4.0
Classifier: License :: OSI Approved :: MIT License
Classifier: Programming Language :: Python :: 3
Classifier: Programming Language :: Python :: 3.10
Classifier: Programming Language :: Python :: 3.11
Classifier: Programming Language :: Python :: 3.12
Requires-Dist: ipython (>=8.23.0,<9.0.0)
Requires-Dist: pandas (>=2.2.1,<3.0.0)
Requires-Dist: pandera (>=0.18.3,<0.19.0)
